setup.cfg
setup.py
OPML_Methods/AdjGrad.py
OPML_Methods/AdjointGrad.py
OPML_Methods/BFGS.py
OPML_Methods/BrentMet_var2.py
OPML_Methods/BrentMet_var2_help.py
OPML_Methods/ExpRegres.py
OPML_Methods/FastGradDesent.py
OPML_Methods/GoldenSection.py
OPML_Methods/Gomory.py
OPML_Methods/GradDesentConstStep.py
OPML_Methods/GradDesentDrobStep.py
OPML_Methods/LinRegr.py
OPML_Methods/MethodLagranja.py
OPML_Methods/Newton.py
OPML_Methods/PEGASOS.py
OPML_Methods/PolRegres.py
OPML_Methods/PorabolMet.py
OPML_Methods/Pryam.py
OPML_Methods/Pryam_dvoy.py
OPML_Methods/SGD.py
OPML_Methods/SearchExtremes.py
OPML_Methods/UserClass.py
OPML_Methods/VetveyGranits.py
OPML_Methods/__init__.py
OPML_Methods/brent.py
OPML_Methods/input_validation.py
OPML_Methods/lab7.py
OPML_Methods/prepocessing.py
OPML_Methods/Сlassification.py
OPML_Methods.egg-info/PKG-INFO
OPML_Methods.egg-info/SOURCES.txt
OPML_Methods.egg-info/dependency_links.txt
OPML_Methods.egg-info/not-zip-safe
OPML_Methods.egg-info/top_level.txt