Metadata-Version: 2.1
Name: OPML-Methods
Version: 0.1.14
Summary: Too much math methods
Home-page: UNKNOWN
Author-email: alexekozikl@mail.ru
License: UNKNOWN
Platform: UNKNOWN
